aracnid_api/__init__.py
aracnid_api/i_airtable.py
aracnid_api-2.2.0.dist-info/LICENSE
aracnid_api-2.2.0.dist-info/METADATA
aracnid_api-2.2.0.dist-info/WHEEL
aracnid_api-2.2.0.dist-info/RECORD
