Metadata-Version: 2.1
Name: aracnid-api
Version: 2.2.0
Summary: This package contains custom wrappers around a variety of Web App APIs.
Home-page: https://github.com/aracnid/aracnid-api
License: MIT
Keywords: api,airtable
Author: Jason Romano
Author-email: aracnid@gmail.com
Requires-Python: >=3.10,<4.0
Classifier: License :: OSI Approved :: MIT License
Classifier: Programming Language :: Python :: 3
Classifier: Programming Language :: Python :: 3.10
Classifier: Programming Language :: Python :: 3.11
Classifier: Programming Language :: Python :: 3.12
Requires-Dist: aracnid-logger (>=1.0,<2.0)
Requires-Dist: pyairtable (>=2.3,<3.0)
Requires-Dist: python-dateutil (==2.8.2)
Project-URL: Repository, https://github.com/aracnid/aracnid-api
